pytest_uuid/__init__.py
pytest_uuid/_import_hook.py
pytest_uuid/_tracking.py
pytest_uuid/api.py
pytest_uuid/config.py
pytest_uuid/generators.py
pytest_uuid/plugin.py
pytest_uuid/py.typed
pytest_uuid/types.py
pytest_uuid-0.4.0.dist-info/WHEEL
pytest_uuid-0.4.0.dist-info/entry_points.txt
pytest_uuid-0.4.0.dist-info/METADATA
pytest_uuid-0.4.0.dist-info/RECORD
