Metadata-Version: 2.4
Name: pytest-uuid
Version: 0.4.0
Summary: A pytest plugin for mocking uuid.uuid4() calls
Keywords: pytest,plugin,uuid,mock,testing
Author: CaptainDriftwood
License-Expression: MIT
Classifier: Development Status :: 4 - Beta
Classifier: Framework :: Pytest
Classifier: Intended Audience :: Developers
Classifier: License :: OSI Approved :: MIT License
Classifier: Operating System :: OS Independent
Classifier: Programming Language :: Python
Classifier: Programming Language :: Python :: 3
Classifier: Programming Language :: Python :: 3.9
Classifier: Programming Language :: Python :: 3.10
Classifier: Programming Language :: Python :: 3.11
Classifier: Programming Language :: Python :: 3.12
Classifier: Programming Language :: Python :: 3.13
Classifier: Programming Language :: Python :: 3.14
Classifier: Topic :: Software Development :: Libraries :: Python Modules
Classifier: Topic :: Software Development :: Testing
Classifier: Topic :: Software Development :: Testing :: Mocking
Classifier: Topic :: Software Development :: Testing :: Unit
Requires-Dist: pytest>=7.0.0
Requires-Dist: tomli>=2.0.0 ; python_full_version < '3.11'
Requires-Python: >=3.9
Project-URL: Documentation, https://captaindriftwood.github.io/pytest-uuid/
Project-URL: Homepage, https://github.com/CaptainDriftwood/pytest-uuid
Project-URL: Issues, https://github.com/CaptainDriftwood/pytest-uuid/issues
Project-URL: Repository, https://github.com/CaptainDriftwood/pytest-uuid
